.gitignore
MANIFEST.in
README.rst
TODO.txt
setup.py
vs.dashboardmanager-configure.zcml
docs/HISTORY.rst
docs/INSTALL.txt
docs/LICENSE.GPL
docs/LICENSE.txt
vs/__init__.py
vs.dashboardmanager.egg-info/PKG-INFO
vs.dashboardmanager.egg-info/SOURCES.txt
vs.dashboardmanager.egg-info/dependency_links.txt
vs.dashboardmanager.egg-info/entry_points.txt
vs.dashboardmanager.egg-info/namespace_packages.txt
vs.dashboardmanager.egg-info/not-zip-safe
vs.dashboardmanager.egg-info/requires.txt
vs.dashboardmanager.egg-info/top_level.txt
vs/dashboardmanager/__init__.py
vs/dashboardmanager/config.py
vs/dashboardmanager/configure.zcml
vs/dashboardmanager/extenders.py
vs/dashboardmanager/header.txt
vs/dashboardmanager/interfaces.py
vs/dashboardmanager/logger.py
vs/dashboardmanager/profiles.zcml
vs/dashboardmanager/retriever.py
vs/dashboardmanager/setuphandlers.py
vs/dashboardmanager/version.txt
vs/dashboardmanager/browser/__init__.py
vs/dashboardmanager/browser/assignments.pt
vs/dashboardmanager/browser/assignments.py
vs/dashboardmanager/browser/configure.zcml
vs/dashboardmanager/browser/interfaces.py
vs/dashboardmanager/browser/management.pt
vs/dashboardmanager/browser/manager.py
vs/dashboardmanager/browser/my-dashboard-pages.pt
vs/dashboardmanager/browser/overrides.zcml
vs/dashboardmanager/browser/portletpage-column.pt
vs/dashboardmanager/browser/portletpage-edit.pt
vs/dashboardmanager/browser/portletpage.pt
vs/dashboardmanager/browser/portletpage.py
vs/dashboardmanager/browser/portletpage_edit.py
vs/dashboardmanager/browser/view-assignments.pt
vs/dashboardmanager/browser/viewlet.pt
vs/dashboardmanager/browser/viewlets.py
vs/dashboardmanager/browser/images/README.txt
vs/dashboardmanager/browser/resources/dashboardmanager.css
vs/dashboardmanager/browser/resources/indicator.gif
vs/dashboardmanager/browser/resources/jquery.autocomplete.css
vs/dashboardmanager/browser/resources/jquery.autocomplete.js
vs/dashboardmanager/browser/stylesheets/README.txt
vs/dashboardmanager/browser/stylesheets/main.css
vs/dashboardmanager/content/__init__.py
vs/dashboardmanager/content/configure.zcml
vs/dashboardmanager/content/dashboardmanager.py
vs/dashboardmanager/locales/README.txt
vs/dashboardmanager/locales/vs.dashboardmanager.pot
vs/dashboardmanager/locales/de/LC_MESSAGES/vs.dashboardmanager.mo
