Metadata-Version: 1.1
Name: vs.dashboardmanager
Version: 0.3.5
Summary: An extended Dashboard manager based on collective.portletpage
Home-page: http://pypi.python.org/pypi/vs.dashboardmanager
Author: Andreas Jung
Author-email: info@zopyx.com
License: GPL
Platform: UNKNOWN
Classifier: Framework :: Plone
Classifier: Programming Language :: Python
